pyvivintsky/__init__.py
pyvivintsky/vivint_api.py
pyvivintsky/vivint_device.py
pyvivintsky/vivint_panel.py
pyvivintsky/vivint_pubnub_callback.py
pyvivintsky/vivint_sky.py
pyvivintsky/vivint_unknown_device.py
pyvivintsky/vivint_wireless_sensor.py
pyVivintSky-0.0.2.dist-info/LICENSE
pyVivintSky-0.0.2.dist-info/METADATA
pyVivintSky-0.0.2.dist-info/WHEEL
pyVivintSky-0.0.2.dist-info/top_level.txt
pyVivintSky-0.0.2.dist-info/RECORD
