Metadata-Version: 2.1
Name: pyVivintSky
Version: 0.0.2
Summary: Python library for interacting with Vivint Sky API
Home-page: https://github.com/silvertoken/pyvivintsky
Author: Will Oldenburg
Author-email: silvertoken99@gmail.com
License: MIT
Keywords: vivint
Platform: UNKNOWN
Classifier: Programming Language :: Python :: 3
Classifier: License :: OSI Approved :: MIT License
Classifier: Operating System :: OS Independent
Requires-Python: >=3.6
Requires-Dist: aiohttp (>=3.6)
Requires-Dist: pubnub (>=4.5)
